[
    { "word": "ğ“¹", "tl": "ê½rê½", "jp": "ä½œã‚‹","tags": ["ME"] },
    { "word": "ğ“‡‹ğ“…±", "tl": "ê½w", "jp": "ï¼ˆä¸å¤‰åŒ–è©ï¼‰", "tags": ["ME"]},
    { "word": "ğ“ˆ™\ud80d\udc30ğ“ˆ–\ud80d\udc30ğ“ˆ–\ud80d\udc30ğ“ˆ–ğ“‡³", "tl": "Å¡mw", "tags": ["ME"]},
    { "word": "ğ“‚‹\ud80d\udc30ğ“ˆ™ğ“…±\ud80d\udc34ğ“ğ“‚‰ğ“›\ud80d\udc30ğ“¥", "tl": "rÅ¡wt", "jp": "å–œã³", "tags": ["ME"]},
    { "word": "ğ“…­\ud80d\udc34ğ“‡³ğ“¹\ud80d\udc3cğ“‡‹ğ“ \ud80d\udc30ğ“ˆ–\ud80d\udc30ğ“ˆ˜ğ“‡³\ud80d\udc30ğ“¤ğ“„Ÿğ“‹´ğ“‡“\ud80d\udc3dğ“º", "tl": "rêœ¥msê½swmrê½ê½mn", "jp": "ãƒ©ãƒ¡ã‚»ã‚¹", "tags": ["ME"]},
    { "word": "ğ“‹¹ğ“ˆ–\ud80d\udc30ğ“", "tl": "êœ¥ná¸«", "jp": "ç”Ÿãã‚‹", "tags": ["ME"]},
    { "word": "ğ“ƒ¹\ud80d\udc30ğ“ˆ–\ud80d\udc30ğ“ˆ–", "tl": "wnn", "jp": "ã‚ã‚‹", "tags": ["ME"]},
    { "word": "ğ“Šƒ\ud80d\udc30ğ“€€\ud80d\udc31ğ“¤", "tl": "z", "jp": "ç”·", "tags": ["ME"]},
    { "word": "ğ“ˆ—", "tl": "mw", "jp": "æ°´", "tags": ["ME"]}
]